{"schema": "mac.worker_evidence.v1", "status": "complete", "evidence_type": "repo_change", "repo": {"head_sha": "2ac7741fcde7a195c856ef166626d51113ad1d7a", "remote_ref": "origin/main", "pushed": false, "dirty": false, "files_changed": ["tests/test_ringbuf.c"], "tests": {"command": "make test-quick", "returncode": 0, "status": "pass", "result": "passed"}}, "codegraph": {"init": "codegraph init -- indexed 452 files, 10439 nodes, 35371 edges", "affected": "codegraph affected tests/test_ringbuf.c -- no test files affected (test-only change)", "notes": "Change is test-only; no production source files modified. No implementation defects found; ringbuf API behaves per documented contract."}, "notes": "Added three focused regression tests to tests/test_ringbuf.c: (R1) failed push on full buffer preserves count and FIFO contents, (R2) failed pop on empty buffer leaves caller output unchanged, (R3) failed peek on empty buffer leaves caller output unchanged. All 234 tests pass. make test-quick passes. Tests registered in test-units via test-ringbuf target in Makefile.gnu."}